[
    {
        "id": 8,
        "title": "Thinking, Fast and Slow",
        "author": "Daniel Kahneman",
        "price": 15200
    },
    {
        "id": 9,
        "title": "The Subtle Art of Not Giving a F*",
        "author": "Mark Manson",
        "price": 16200
    },
    {
        "id": 10,
        "title": "The Diary of a Young Girl",
        "author": "Anne Frank",
        "price": 7880
    },
    {
        "id": 11,
        "title": "The Alchemist",
        "author": "Paulo Coelho",
        "price": 12150
    }
]
